odoo/addons/product_supplierinfo_import/README.rst
odoo/addons/product_supplierinfo_import/__init__.py
odoo/addons/product_supplierinfo_import/__manifest__.py
odoo/addons/product_supplierinfo_import/i18n/es.po
odoo/addons/product_supplierinfo_import/i18n/it.po
odoo/addons/product_supplierinfo_import/i18n/product_supplierinfo_import.pot
odoo/addons/product_supplierinfo_import/models/__init__.py
odoo/addons/product_supplierinfo_import/models/product_supplier_info.py
odoo/addons/product_supplierinfo_import/models/product_supplierinfo_import_template.py
odoo/addons/product_supplierinfo_import/models/product_template.py
odoo/addons/product_supplierinfo_import/readme/CONFIGURE.md
odoo/addons/product_supplierinfo_import/readme/CONTRIBUTORS.md
odoo/addons/product_supplierinfo_import/readme/DESCRIPTION.md
odoo/addons/product_supplierinfo_import/readme/USAGE.md
odoo/addons/product_supplierinfo_import/security/ir.model.access.csv
odoo/addons/product_supplierinfo_import/static/description/icon.png
odoo/addons/product_supplierinfo_import/static/description/index.html
odoo/addons/product_supplierinfo_import/tests/__init__.py
odoo/addons/product_supplierinfo_import/tests/test_product_supplierinfo_import.py
odoo/addons/product_supplierinfo_import/tests/data/test_supplier_drinks_complex_sheet.xlsx
odoo/addons/product_supplierinfo_import/tests/data/test_supplier_drinks_complex_sheet_updated.xlsx
odoo/addons/product_supplierinfo_import/tests/data/test_supplier_spanish_drinks.xlsx
odoo/addons/product_supplierinfo_import/views/product_supplierinfo_import_template_views.xml
odoo/addons/product_supplierinfo_import/wizards/__init__.py
odoo/addons/product_supplierinfo_import/wizards/product_supplierinfo_import.py
odoo/addons/product_supplierinfo_import/wizards/product_supplierinfo_import_views.xml
odoo_addon_product_supplierinfo_import-18.0.1.0.1.dist-info/METADATA
odoo_addon_product_supplierinfo_import-18.0.1.0.1.dist-info/WHEEL
odoo_addon_product_supplierinfo_import-18.0.1.0.1.dist-info/top_level.txt
odoo_addon_product_supplierinfo_import-18.0.1.0.1.dist-info/RECORD
